<Metadata xmlns="http://rep.oio.dk/infostructurebase/schemas/2004/09/13/">
  <Title>OrganizationalUnit</Title>
  <DescriptionStructure>
    <DescriptionEnglish />
    <DescriptionDanish>Oplysninger relateret til den organisatoriske enhed (navn, SghAfd-kode, type, adresse mv).</DescriptionDanish>
  </DescriptionStructure>
  <Author>Sundhedsstyrelsen, SOR</Author>
  <LabelStructure>
    <LabelDanish>Organisatorisk enhed</LabelDanish>
  </LabelStructure>
  <ObjectTerm>Adresse</ObjectTerm>
  <PropertyTerm></PropertyTerm>
  <RepresentationTerm></RepresentationTerm>
  <Version>1.0.0</Version>
</Metadata>

